mdx_math_svg.py
mdx_math_svg-1.2.2.dist-info/LICENSE
mdx_math_svg-1.2.2.dist-info/METADATA
mdx_math_svg-1.2.2.dist-info/WHEEL
mdx_math_svg-1.2.2.dist-info/entry_points.txt
mdx_math_svg-1.2.2.dist-info/top_level.txt
mdx_math_svg-1.2.2.dist-info/RECORD
