Metadata-Version: 2.1
Name: mdx_math_svg
Version: 1.2.2
Summary: SVG Math extension for Python-Markdown
Home-page: https://github.com/crisluengo/mdx_math_svg
Author: Cris Luengo
Author-email: lueng@ieee.org
License: MIT
Classifier: Development Status :: 5 - Production/Stable
Classifier: License :: OSI Approved :: MIT License
Classifier: Operating System :: OS Independent
Classifier: Programming Language :: Python
Classifier: Programming Language :: Python :: 3
Classifier: Programming Language :: Python :: 3 :: Only
Classifier: Programming Language :: Python :: 3.6
Classifier: Programming Language :: Python :: 3.7
Classifier: Programming Language :: Python :: 3.8
Classifier: Programming Language :: Python :: 3.9
Classifier: Programming Language :: Python :: 3.10
Classifier: Programming Language :: Python :: 3.11
Classifier: Programming Language :: Python :: 3.12
Classifier: Topic :: Scientific/Engineering :: Mathematics
Classifier: Topic :: Text Processing :: Markup :: Markdown
Requires-Python: >=3.6
License-File: LICENSE
Requires-Dist: Markdown>=3.0
